genomemanagement/PlantPAN2.py
genomemanagement/PlantPAN3.py
genomemanagement/__init__.py
genomemanagement/get_genome_statistic.py
genomemanagement/memeXml2bed.py
genomemanagement/promoter_retrieve.py
genomemanagement/proteins_retrieve.py
genomemanagement/seq_manage.py
genomemanagement-2.0.0.dist-info/licenses/LICENSE
genomemanagement-2.0.0.dist-info/METADATA
genomemanagement-2.0.0.dist-info/WHEEL
genomemanagement-2.0.0.dist-info/entry_points.txt
genomemanagement-2.0.0.dist-info/top_level.txt
genomemanagement-2.0.0.dist-info/RECORD
