Metadata-Version: 2.4
Name: genomemanagement
Version: 2.0.0
Summary: Genome Management Package
Author-email: Nattawet Sriwichai <nattawet.sri@mail.kmutt.ac.th>
Classifier: Programming Language :: Python :: 3
Classifier: License :: OSI Approved :: MIT License
Classifier: Operating System :: OS Independent
Requires-Python: >=3.7
License-File: LICENSE
Provides-Extra: dev
Requires-Dist: pytest; extra == "dev"
Requires-Dist: build; extra == "dev"
Requires-Dist: twine; extra == "dev"
Provides-Extra: test
Requires-Dist: pytest; extra == "test"
Dynamic: license-file
